precice_config_format-1.2.1.dist-info/licenses/LICENSE
preciceconfigformat/cli.py
precice_config_format-1.2.1.dist-info/METADATA
precice_config_format-1.2.1.dist-info/WHEEL
precice_config_format-1.2.1.dist-info/entry_points.txt
precice_config_format-1.2.1.dist-info/top_level.txt
precice_config_format-1.2.1.dist-info/RECORD
