Metadata-Version: 2.4
Name: precice-config-format
Version: 1.2.1
Summary: A tool for consistently formatting a preCICE configuration file.
Author-email: The preCICE Developers <info@precice.org>
Maintainer-email: Frédéric Simonis <frederic.simonis@ipvs.uni-stuttgart.de>
License-Expression: GPL-3.0-or-later
Project-URL: Homepage, https://precice.org
Project-URL: Repository, https://github.com/precice/config-format.git
Project-URL: Bug Tracker, https://github.com/precice/config-format/issues
Keywords: preCICE,XML,configuration,format,formatter
Classifier: Development Status :: 4 - Beta
Classifier: Programming Language :: Python :: 3 :: Only
Classifier: Programming Language :: Python :: 3.8
Classifier: Topic :: Utilities
Requires-Python: >=3.8
License-File: LICENSE
Requires-Dist: lxml
Dynamic: license-file
